llm_term/__about__.py
llm_term/__init__.py
llm_term/__main__.py
llm_term/base.py
llm_term/cli.py
llm_term/py.typed
llm_term/utils.py
llm_term-0.14.0.dist-info/METADATA
llm_term-0.14.0.dist-info/WHEEL
llm_term-0.14.0.dist-info/entry_points.txt
llm_term-0.14.0.dist-info/licenses/LICENSE
llm_term-0.14.0.dist-info/RECORD
