Metadata-Version: 2.3
Name: llm-term
Version: 0.14.0
Summary: A simple CLI to chat with LLM Models
Project-URL: Changelog, https://github.com/juftin/llm-term/releases
Project-URL: Documentation, https://juftin.github.io/llm-term
Project-URL: Issues, https://juftin.github.io/llm-term/issues
Project-URL: Source, https://github.com/juftin/llm-term
Author-email: Justin Flannery <juftin@juftin.com>
License-Expression: MIT
License-File: LICENSE
Keywords: chatgpt,cli,openai,python,rich
Classifier: Development Status :: 5 - Production/Stable
Classifier: Operating System :: OS Independent
Classifier: Programming Language :: Python
Classifier: Programming Language :: Python :: 3.8
Classifier: Programming Language :: Python :: 3.9
Classifier: Programming Language :: Python :: 3.10
Classifier: Programming Language :: Python :: 3.11
Classifier: Programming Language :: Python :: 3.12
Classifier: Programming Language :: Python :: Implementation :: CPython
Classifier: Programming Language :: Python :: Implementation :: PyPy
Requires-Python: <4,>=3.8
Requires-Dist: click~=8.1.7
Requires-Dist: langchain-community~=0.2.7
Requires-Dist: langchain-openai~=0.1.17
Requires-Dist: langchain~=0.2.9
Requires-Dist: numpy~=1.24.4; python_version < '3.9'
Requires-Dist: numpy~=1.26.1; python_version > '3.8'
Requires-Dist: prompt-toolkit~=3.0.39
Requires-Dist: rich~=13.5.3
Provides-Extra: all
Requires-Dist: langchain-anthropic~=0.1.20; extra == 'all'
Requires-Dist: langchain-mistralai~=0.1.10; extra == 'all'
Provides-Extra: anthropic
Requires-Dist: langchain-anthropic~=0.1.20; extra == 'anthropic'
Provides-Extra: mistralai
Requires-Dist: langchain-mistralai~=0.1.10; extra == 'mistralai'
